MANIFEST.in
info.py
requirements.txt
setup.py
version.py
mysqlqueryresult2dict/__init__.py
mysqlqueryresult2dict/mysqlqueryresult2dict.py
mysqlqueryresult2dict.egg-info/PKG-INFO
mysqlqueryresult2dict.egg-info/SOURCES.txt
mysqlqueryresult2dict.egg-info/dependency_links.txt
mysqlqueryresult2dict.egg-info/top_level.txt