Metadata-Version: 1.1
Name: mysqlqueryresult2dict
Version: 0.0.1
Summary: Create dict from MySQL query result text.
Home-page: https://github.com/koyachi/mysqlqueryresult2dict
Author: koyachi
Author-email: rtk2106@gmail.com
License: MIT License
Platform: UNKNOWN
Classifier: Programming Language :: Python :: 2.7
Classifier: License :: OSI Approved :: MIT License
